<?xml version = '1.0' encoding = 'UTF-8'?>
<Diagram class="oracle.dbtools.crest.swingui.relational.DPVRelational" name="Relational_1" id="47E70ED7-5C5E-9DC5-4C17-AD6941B9F414">
<createdBy>Alexander Marquez</createdBy>
<modifiedBy>Alexander Marquez</modifiedBy>
<createdTime>2026-05-20 19:41:23 UTC</createdTime>
<autoRoute>false</autoRoute>
<boxInbox>true</boxInbox>
<showLegend>false</showLegend>
<showLabels>true</showLabels>
<showRelAttributes>false</showRelAttributes>
<gridEnabled>false</gridEnabled>
<showGrid>true</showGrid>
<diagramColor>-1</diagramColor>
<display>false</display>
<notation>1</notation>
<objectViews>
<OView class="oracle.dbtools.crest.swingui.relational.TVTable" oid="010014AD-77F9-B470-76C7-F1D543FFC0CC" otype="Table" vid="BB7035FC-DAFB-BEC1-77EE-F352EEAE480F">
<hideElementsInCurrentOnly>false</hideElementsInCurrentOnly>
<bounds x="397" y="1857" width="346" height="220"/>
</OView>
<OView class="oracle.dbtools.crest.swingui.relational.TVTable" oid="0E547F61-4840-7314-4A27-A611F35A7E59" otype="Table" vid="BA7581E3-C45F-CE3E-8CE5-477A6EEAB6B4">
<hideElementsInCurrentOnly>false</hideElementsInCurrentOnly>
<bounds x="2980" y="2077" width="333" height="229"/>
</OView>
<OView class="oracle.dbtools.crest.swingui.relational.TVTable" oid="10E618BC-1EFA-F30D-196F-437339118551" otype="Table" vid="4336DF47-1917-A176-1867-DC74E2ABC491">
<hideElementsInCurrentOnly>false</hideElementsInCurrentOnly>
<bounds x="968" y="2425" width="349" height="265"/>
</OView>
<OView class="oracle.dbtools.crest.swingui.relational.TVTable" oid="16FD1E12-05C2-3F98-4F6C-E690C56859F8" otype="Table" vid="966ACDC1-7DCB-7798-79EB-A7880CC4D1C1">
<hideElementsInCurrentOnly>false</hideElementsInCurrentOnly>
<bounds x="2424" y="646" width="355" height="290"/>
</OView>
<OView class="oracle.dbtools.crest.swingui.relational.TVTable" oid="1815267B-898F-AD67-CBBE-45BA167573D8" otype="Table" vid="208205D6-BB37-5991-61BB-5FFC6A0020E8">
<hideElementsInCurrentOnly>false</hideElementsInCurrentOnly>
<bounds x="0" y="953" width="326" height="257"/>
</OView>
<OView class="oracle.dbtools.crest.swingui.relational.TVTable" oid="1A4BDDF1-E3E1-DD22-BC09-C53BCC4F5572" otype="Table" vid="E455054E-209D-8758-F0AA-C9367F92EBF3">
<hideElementsInCurrentOnly>false</hideElementsInCurrentOnly>
<bounds x="1501" y="1734" width="321" height="389"/>
</OView>
<OView class="oracle.dbtools.crest.swingui.relational.TVTable" oid="22A6307C-D3DA-27F0-07F3-F5865E0F2770" otype="Table" vid="C338C895-DEE4-517C-039B-6B2649E00025">
<hideElementsInCurrentOnly>false</hideElementsInCurrentOnly>
<bounds x="20" y="1857" width="327" height="346"/>
</OView>
<OView class="oracle.dbtools.crest.swingui.relational.TVTable" oid="373E9136-526C-3258-EFF1-D2F7FD6B89C7" otype="Table" vid="681B5C5D-866E-D2EA-58E7-6B74CC242C90">
<hideElementsInCurrentOnly>false</hideElementsInCurrentOnly>
<bounds x="3005" y="1456" width="281" height="280"/>
</OView>
<OView class="oracle.dbtools.crest.swingui.relational.TVTable" oid="3B719D8D-4B06-9B7C-B71B-591791E53FDD" otype="Table" vid="9DA066B0-E210-71E4-25EB-A97C92A81DF9">
<hideElementsInCurrentOnly>false</hideElementsInCurrentOnly>
<bounds x="476" y="650" width="353" height="1063"/>
</OView>
<OView class="oracle.dbtools.crest.swingui.relational.TVTable" oid="4678378E-1222-8C16-7937-7D6402845012" otype="Table" vid="1D555976-D44B-2C4F-C70D-DFE5CB8B4AD2">
<hideElementsInCurrentOnly>false</hideElementsInCurrentOnly>
<bounds x="3001" y="1777" width="304" height="286"/>
</OView>
<OView class="oracle.dbtools.crest.swingui.relational.TVTable" oid="4C0EAE1C-534A-F434-3F06-CDE33C5E8B7F" otype="Table" vid="EBCB4760-6EE8-4118-49D2-FE8E6B67D156">
<hideElementsInCurrentOnly>false</hideElementsInCurrentOnly>
<bounds x="2436" y="1696" width="380" height="532"/>
</OView>
<OView class="oracle.dbtools.crest.swingui.relational.TVTable" oid="58C4E816-7BFD-D50F-B834-20C766D438BA" otype="Table" vid="E1EE40A7-ACC1-54A1-0242-1D9E4EF254E6">
<hideElementsInCurrentOnly>false</hideElementsInCurrentOnly>
<bounds x="508" y="2354" width="261" height="132"/>
</OView>
<OView class="oracle.dbtools.crest.swingui.relational.TVTable" oid="59CF3D14-AA95-09FE-8443-CD3C26500162" otype="Table" vid="9FD32447-5499-BFEB-954E-B29C9E21A372">
<hideElementsInCurrentOnly>false</hideElementsInCurrentOnly>
<bounds x="20" y="2353" width="303" height="262"/>
</OView>
<OView class="oracle.dbtools.crest.swingui.relational.TVTable" oid="5C603DFA-5CAD-018F-FADC-92B0EDABAF17" otype="Table" vid="961EA11C-9323-C677-CA20-2F0045C0711A">
<hideElementsInCurrentOnly>false</hideElementsInCurrentOnly>
<bounds x="829" y="1774" width="307" height="312"/>
</OView>
<OView class="oracle.dbtools.crest.swingui.relational.TVTable" oid="678989F0-B2FB-C0EC-14A7-842BBA4252BA" otype="Table" vid="F8342A33-0870-DFD8-27F8-639EE9B01088">
<hideElementsInCurrentOnly>false</hideElementsInCurrentOnly>
<bounds x="1376" y="564" width="344" height="359"/>
</OView>
<OView class="oracle.dbtools.crest.swingui.relational.TVTable" oid="6DA31E2D-3D00-5141-750E-78E14358E61F" otype="Table" vid="05D9F997-7828-0148-5902-694272C796AE">
<hideElementsInCurrentOnly>false</hideElementsInCurrentOnly>
<bounds x="971" y="2709" width="318" height="157"/>
</OView>
<OView class="oracle.dbtools.crest.swingui.relational.TVTable" oid="71FF344E-E414-8E1A-2544-B4667E4E0F5D" otype="Table" vid="B8E0C93C-5534-6B2D-DC1C-EBEC97E2AF24">
<hideElementsInCurrentOnly>false</hideElementsInCurrentOnly>
<bounds x="1656" y="2372" width="392" height="370"/>
</OView>
<OView class="oracle.dbtools.crest.swingui.relational.TVTable" oid="8AA965B1-7B3D-18DC-F550-3234BEB53F17" otype="Table" vid="7B6F633D-9E8C-5732-79C2-C72BBE67CA6C">
<hideElementsInCurrentOnly>false</hideElementsInCurrentOnly>
<bounds x="1385" y="2972" width="293" height="173"/>
</OView>
<OView class="oracle.dbtools.crest.swingui.relational.TVTable" oid="937E4462-1BD9-B423-9D86-F04C885D9131" otype="Table" vid="C3DB015C-EA85-0F9A-678E-8C328DB104EC">
<hideElementsInCurrentOnly>false</hideElementsInCurrentOnly>
<bounds x="1860" y="557" width="370" height="455"/>
</OView>
<OView class="oracle.dbtools.crest.swingui.relational.TVTable" oid="9A960869-D288-1B29-D1CD-0BEAB0B8F720" otype="Table" vid="980E517A-93CC-EABF-09BC-A46036512BA8">
<hideElementsInCurrentOnly>false</hideElementsInCurrentOnly>
<bounds x="974" y="2236" width="363" height="175"/>
</OView>
<OView class="oracle.dbtools.crest.swingui.relational.TVTable" oid="A6A3D2D7-D592-8B27-18A9-F32CE0BF096A" otype="Table" vid="8C77506B-B0FD-6F9A-E569-0A98B8EF3DAD">
<hideElementsInCurrentOnly>false</hideElementsInCurrentOnly>
<bounds x="455" y="2131" width="355" height="221"/>
</OView>
<OView class="oracle.dbtools.crest.swingui.relational.TVTable" oid="AFD33838-9B21-4527-10E5-29D613C52BE5" otype="Table" vid="BC9718B1-702B-391C-9972-6098DC19CD45">
<hideElementsInCurrentOnly>false</hideElementsInCurrentOnly>
<bounds x="1770" y="2887" width="325" height="299"/>
</OView>
<OView class="oracle.dbtools.crest.swingui.relational.TVTable" oid="B4B46052-AD3D-3A00-FDBB-F3AC58A29488" otype="Table" vid="5A8EEA4E-CE12-CE96-F336-5C4000C4D31D">
<hideElementsInCurrentOnly>false</hideElementsInCurrentOnly>
<bounds x="2986" y="1195" width="279" height="196"/>
</OView>
<OView class="oracle.dbtools.crest.swingui.relational.TVTable" oid="BE0449EE-2DBC-F20F-2AD7-004E6DA9D199" otype="Table" vid="D7FB553C-F128-0BB8-EE80-FFCB02811AD1">
<hideElementsInCurrentOnly>false</hideElementsInCurrentOnly>
<bounds x="2512" y="2957" width="323" height="180"/>
</OView>
<OView class="oracle.dbtools.crest.swingui.relational.TVTable" oid="E5F44B71-0DFB-B653-4D69-FC0DB511E512" otype="Table" vid="A25D8B15-42D0-A6E0-2533-B68A3E1B62DF">
<hideElementsInCurrentOnly>false</hideElementsInCurrentOnly>
<bounds x="1907" y="1722" width="352" height="398"/>
</OView>
<OView class="oracle.dbtools.crest.swingui.relational.TVTable" oid="F01A64E0-704E-0D26-6705-C5F384BC4BE2" otype="Table" vid="A445D075-2ABD-0EA5-A369-1F9D5305112B">
<hideElementsInCurrentOnly>false</hideElementsInCurrentOnly>
<bounds x="2202" y="1087" width="288" height="328"/>
</OView>
<OView class="oracle.dbtools.crest.swingui.relational.TVTable" oid="F616A4BB-50DC-8A6D-ABC7-F210FAB2099A" otype="Table" vid="026C8DC3-6748-AC95-0D69-DE4FCB4D30AD">
<hideElementsInCurrentOnly>false</hideElementsInCurrentOnly>
<bounds x="1590" y="1252" width="280" height="261"/>
</OView>
<OView class="oracle.dbtools.crest.swingui.relational.TVTable" oid="FEB0E130-0811-72E5-FBF0-1C51BC7F70FF" otype="Table" vid="6A7DC662-89AE-DCDF-C062-D1C0DC82047F">
<hideElementsInCurrentOnly>false</hideElementsInCurrentOnly>
<bounds x="2985" y="2381" width="303" height="181"/>
</OView>
</objectViews>
<connectors>
<Connector class="oracle.dbtools.crest.swingui.relational.TVFKRelation" oid="0121F2F1-67DD-D802-1271-E990C3B12868" otype="FKIndexAssociation" vid_source="C3DB015C-EA85-0F9A-678E-8C328DB104EC" vid_target="F8342A33-0870-DFD8-27F8-639EE9B01088">
<hideElementsInCurrentOnly>false</hideElementsInCurrentOnly>
<backgroundColor>-16777216</backgroundColor>
<lineWidth>1</lineWidth>
<centerLabel class="oracle.dbtools.crest.model.design.Label">
<site>1</site>
<labelBounds x="-109" y="-31" width="109" height="30"/>
<noBackgroundColor>true</noBackgroundColor>
<noForegroundColor>true</noForegroundColor>
</centerLabel>
<points>
<point x="1860" y="743"/>
<point x="1720" y="743"/>
</points>
</Connector>
<Connector class="oracle.dbtools.crest.swingui.relational.TVFKRelation" oid="032D639B-13DA-D38F-9FBB-7772D1562AAA" otype="FKIndexAssociation" vid_source="B8E0C93C-5534-6B2D-DC1C-EBEC97E2AF24" vid_target="7B6F633D-9E8C-5732-79C2-C72BBE67CA6C">
<hideElementsInCurrentOnly>false</hideElementsInCurrentOnly>
<backgroundColor>-16777216</backgroundColor>
<lineWidth>1</lineWidth>
<centerLabel class="oracle.dbtools.crest.model.design.Label">
<site>1</site>
<labelBounds x="-65" y="-31" width="65" height="30"/>
<noBackgroundColor>true</noBackgroundColor>
<noForegroundColor>true</noForegroundColor>
</centerLabel>
<points>
<point x="1667" y="2742"/>
<point x="1667" y="2972"/>
</points>
</Connector>
<Connector class="oracle.dbtools.crest.swingui.relational.TVFKRelation" oid="0528D272-EB56-D0E3-DD4F-679344C4E81B" otype="FKIndexAssociation" vid_source="9DA066B0-E210-71E4-25EB-A97C92A81DF9" vid_target="026C8DC3-6748-AC95-0D69-DE4FCB4D30AD">
<hideElementsInCurrentOnly>false</hideElementsInCurrentOnly>
<backgroundColor>-16777216</backgroundColor>
<lineWidth>1</lineWidth>
<centerLabel class="oracle.dbtools.crest.model.design.Label">
<site>1</site>
<labelBounds x="-67" y="-31" width="67" height="30"/>
<noBackgroundColor>true</noBackgroundColor>
<noForegroundColor>true</noForegroundColor>
</centerLabel>
<points>
<point x="829" y="1367"/>
<point x="1590" y="1367"/>
</points>
</Connector>
<Connector class="oracle.dbtools.crest.swingui.relational.TVFKRelation" oid="0C284834-75BC-D060-E07E-BAAB77CD4EC0" otype="FKIndexAssociation" vid_source="EBCB4760-6EE8-4118-49D2-FE8E6B67D156" vid_target="A445D075-2ABD-0EA5-A369-1F9D5305112B">
<hideElementsInCurrentOnly>false</hideElementsInCurrentOnly>
<backgroundColor>-16777216</backgroundColor>
<lineWidth>1</lineWidth>
<centerLabel class="oracle.dbtools.crest.model.design.Label">
<site>1</site>
<labelBounds x="42" y="1384" width="103" height="2"/>
<noBackgroundColor>true</noBackgroundColor>
<noForegroundColor>true</noForegroundColor>
</centerLabel>
<points>
<point x="2463" y="1696"/>
<point x="2463" y="1415"/>
</points>
</Connector>
<Connector class="oracle.dbtools.crest.swingui.relational.TVFKRelation" oid="1CE6B11B-5B8D-8C39-6521-C6BCABBA0614" otype="FKIndexAssociation" vid_source="681B5C5D-866E-D2EA-58E7-6B74CC242C90" vid_target="9DA066B0-E210-71E4-25EB-A97C92A81DF9">
<hideElementsInCurrentOnly>false</hideElementsInCurrentOnly>
<backgroundColor>-16777216</backgroundColor>
<lineWidth>1</lineWidth>
<centerLabel class="oracle.dbtools.crest.model.design.Label">
<site>1</site>
<labelBounds x="-123" y="-31" width="123" height="30"/>
<noBackgroundColor>true</noBackgroundColor>
<noForegroundColor>true</noForegroundColor>
</centerLabel>
<points>
<point x="3005" y="1584"/>
<point x="829" y="1584"/>
</points>
</Connector>
<Connector class="oracle.dbtools.crest.swingui.relational.TVFKRelation" oid="1D50659A-E7E5-6E74-FF01-B6211AE98320" otype="FKIndexAssociation" vid_source="A445D075-2ABD-0EA5-A369-1F9D5305112B" vid_target="026C8DC3-6748-AC95-0D69-DE4FCB4D30AD">
<hideElementsInCurrentOnly>false</hideElementsInCurrentOnly>
<backgroundColor>-16777216</backgroundColor>
<lineWidth>1</lineWidth>
<centerLabel class="oracle.dbtools.crest.model.design.Label">
<site>1</site>
<labelBounds x="-79" y="-31" width="79" height="30"/>
<noBackgroundColor>true</noBackgroundColor>
<noForegroundColor>true</noForegroundColor>
</centerLabel>
<points>
<point x="2202" y="1333"/>
<point x="1870" y="1333"/>
</points>
</Connector>
<Connector class="oracle.dbtools.crest.swingui.relational.TVFKRelation" oid="1DCA9453-C494-5057-F8B3-7787F5DEC23E" otype="FKIndexAssociation" vid_source="B8E0C93C-5534-6B2D-DC1C-EBEC97E2AF24" vid_target="05D9F997-7828-0148-5902-694272C796AE">
<hideElementsInCurrentOnly>false</hideElementsInCurrentOnly>
<backgroundColor>-16777216</backgroundColor>
<lineWidth>1</lineWidth>
<centerLabel class="oracle.dbtools.crest.model.design.Label">
<site>1</site>
<labelBounds x="-79" y="-31" width="79" height="30"/>
<noBackgroundColor>true</noBackgroundColor>
<noForegroundColor>true</noForegroundColor>
</centerLabel>
<points>
<point x="1656" y="2710"/>
<point x="1289" y="2710"/>
</points>
</Connector>
<Connector class="oracle.dbtools.crest.swingui.relational.TVFKRelation" oid="21BC9CA8-F241-7861-469E-771A2A6857A9" otype="FKIndexAssociation" vid_source="EBCB4760-6EE8-4118-49D2-FE8E6B67D156" vid_target="A25D8B15-42D0-A6E0-2533-B68A3E1B62DF">
<hideElementsInCurrentOnly>false</hideElementsInCurrentOnly>
<backgroundColor>-16777216</backgroundColor>
<lineWidth>1</lineWidth>
<centerLabel class="oracle.dbtools.crest.model.design.Label">
<site>1</site>
<labelBounds x="-67" y="-31" width="67" height="30"/>
<noBackgroundColor>true</noBackgroundColor>
<noForegroundColor>true</noForegroundColor>
</centerLabel>
<points>
<point x="2436" y="1921"/>
<point x="2259" y="1921"/>
</points>
</Connector>
<Connector class="oracle.dbtools.crest.swingui.relational.TVFKRelation" oid="2631F5A2-A982-E248-7E29-8B645E912191" otype="FKIndexAssociation" vid_source="EBCB4760-6EE8-4118-49D2-FE8E6B67D156" vid_target="6A7DC662-89AE-DCDF-C062-D1C0DC82047F">
<hideElementsInCurrentOnly>false</hideElementsInCurrentOnly>
<backgroundColor>-16777216</backgroundColor>
<lineWidth>1</lineWidth>
<centerLabel class="oracle.dbtools.crest.model.design.Label">
<site>1</site>
<labelBounds x="-73" y="-31" width="73" height="30"/>
<noBackgroundColor>true</noBackgroundColor>
<noForegroundColor>true</noForegroundColor>
</centerLabel>
<points>
<point x="2755" y="2228"/>
<point x="3045" y="2381"/>
</points>
</Connector>
<Connector class="oracle.dbtools.crest.swingui.relational.TVFKRelation" oid="2BF892CF-DA43-3AF6-E518-C04DA8D1DD78" otype="FKIndexAssociation" vid_source="B8E0C93C-5534-6B2D-DC1C-EBEC97E2AF24" vid_target="980E517A-93CC-EABF-09BC-A46036512BA8">
<hideElementsInCurrentOnly>false</hideElementsInCurrentOnly>
<backgroundColor>-16777216</backgroundColor>
<lineWidth>1</lineWidth>
<centerLabel class="oracle.dbtools.crest.model.design.Label">
<site>1</site>
<labelBounds x="-79" y="-31" width="79" height="30"/>
<noBackgroundColor>true</noBackgroundColor>
<noForegroundColor>true</noForegroundColor>
</centerLabel>
<points>
<point x="1656" y="2391"/>
<point x="1337" y="2391"/>
</points>
</Connector>
<Connector class="oracle.dbtools.crest.swingui.relational.TVFKRelation" oid="2CF9BCE0-836F-BCAE-D080-5E888EF42769" otype="FKIndexAssociation" vid_source="EBCB4760-6EE8-4118-49D2-FE8E6B67D156" vid_target="5A8EEA4E-CE12-CE96-F336-5C4000C4D31D">
<hideElementsInCurrentOnly>false</hideElementsInCurrentOnly>
<backgroundColor>-16777216</backgroundColor>
<lineWidth>1</lineWidth>
<centerLabel class="oracle.dbtools.crest.model.design.Label">
<site>1</site>
<labelBounds x="-73" y="-31" width="72" height="30"/>
<noBackgroundColor>true</noBackgroundColor>
<noForegroundColor>true</noForegroundColor>
</centerLabel>
<points>
<point x="2816" y="1707"/>
<point x="3052" y="1391"/>
</points>
</Connector>
<Connector class="oracle.dbtools.crest.swingui.relational.TVFKRelation" oid="2F5E8BC0-9C9E-3ADC-8A02-A80CCFA91E3B" otype="FKIndexAssociation" vid_source="A25D8B15-42D0-A6E0-2533-B68A3E1B62DF" vid_target="9DA066B0-E210-71E4-25EB-A97C92A81DF9">
<hideElementsInCurrentOnly>false</hideElementsInCurrentOnly>
<backgroundColor>-16777216</backgroundColor>
<lineWidth>1</lineWidth>
<centerLabel class="oracle.dbtools.crest.model.design.Label">
<site>1</site>
<labelBounds x="-113" y="-31" width="113" height="30"/>
<noBackgroundColor>true</noBackgroundColor>
<noForegroundColor>true</noForegroundColor>
</centerLabel>
<points>
<point x="1907" y="1830"/>
<point x="829" y="1272"/>
</points>
</Connector>
<Connector class="oracle.dbtools.crest.swingui.relational.TVFKRelation" oid="3924CD28-E70B-F64C-137D-BB246B971340" otype="FKIndexAssociation" vid_source="EBCB4760-6EE8-4118-49D2-FE8E6B67D156" vid_target="D7FB553C-F128-0BB8-EE80-FFCB02811AD1">
<hideElementsInCurrentOnly>false</hideElementsInCurrentOnly>
<backgroundColor>-16777216</backgroundColor>
<lineWidth>1</lineWidth>
<centerLabel class="oracle.dbtools.crest.model.design.Label">
<site>1</site>
<labelBounds x="-77" y="-31" width="76" height="30"/>
<noBackgroundColor>true</noBackgroundColor>
<noForegroundColor>true</noForegroundColor>
</centerLabel>
<points>
<point x="2664" y="2228"/>
<point x="2664" y="2957"/>
</points>
</Connector>
<Connector class="oracle.dbtools.crest.swingui.relational.TVFKRelation" oid="394E816F-C6F6-8395-2577-312E26FB068E" otype="FKIndexAssociation" vid_source="B8E0C93C-5534-6B2D-DC1C-EBEC97E2AF24" vid_target="E455054E-209D-8758-F0AA-C9367F92EBF3">
<hideElementsInCurrentOnly>false</hideElementsInCurrentOnly>
<backgroundColor>-16777216</backgroundColor>
<lineWidth>1</lineWidth>
<centerLabel class="oracle.dbtools.crest.model.design.Label">
<site>1</site>
<labelBounds x="-99" y="-31" width="98" height="30"/>
<noBackgroundColor>true</noBackgroundColor>
<noForegroundColor>true</noForegroundColor>
</centerLabel>
<points>
<point x="1739" y="2372"/>
<point x="1739" y="2123"/>
</points>
</Connector>
<Connector class="oracle.dbtools.crest.swingui.relational.TVFKRelation" oid="3AF8DFC3-670D-4230-C389-59CBFE84EE7F" otype="FKIndexAssociation" vid_source="966ACDC1-7DCB-7798-79EB-A7880CC4D1C1" vid_target="A25D8B15-42D0-A6E0-2533-B68A3E1B62DF">
<hideElementsInCurrentOnly>false</hideElementsInCurrentOnly>
<backgroundColor>-16777216</backgroundColor>
<lineWidth>1</lineWidth>
<centerLabel class="oracle.dbtools.crest.model.design.Label">
<site>1</site>
<labelBounds x="-125" y="-31" width="125" height="30"/>
<noBackgroundColor>true</noBackgroundColor>
<noForegroundColor>true</noForegroundColor>
</centerLabel>
<points>
<point x="2534" y="936"/>
<point x="2174" y="1722"/>
</points>
</Connector>
<Connector class="oracle.dbtools.crest.swingui.relational.TVFKRelation" oid="3C6C1EC0-908B-1AB0-844D-805B1E4B6BFD" otype="FKIndexAssociation" vid_source="EBCB4760-6EE8-4118-49D2-FE8E6B67D156" vid_target="966ACDC1-7DCB-7798-79EB-A7880CC4D1C1">
<hideElementsInCurrentOnly>false</hideElementsInCurrentOnly>
<backgroundColor>-16777216</backgroundColor>
<lineWidth>1</lineWidth>
<centerLabel class="oracle.dbtools.crest.model.design.Label">
<site>1</site>
<labelBounds x="-79" y="-31" width="79" height="30"/>
<noBackgroundColor>true</noBackgroundColor>
<noForegroundColor>true</noForegroundColor>
</centerLabel>
<points>
<point x="2607" y="1696"/>
<point x="2607" y="936"/>
</points>
</Connector>
<Connector class="oracle.dbtools.crest.swingui.relational.TVFKRelation" oid="525FC7BC-DF6E-336E-C4ED-E906C5A79F33" otype="FKIndexAssociation" vid_source="EBCB4760-6EE8-4118-49D2-FE8E6B67D156" vid_target="B8E0C93C-5534-6B2D-DC1C-EBEC97E2AF24">
<hideElementsInCurrentOnly>false</hideElementsInCurrentOnly>
<backgroundColor>-16777216</backgroundColor>
<lineWidth>1</lineWidth>
<centerLabel class="oracle.dbtools.crest.model.design.Label">
<site>1</site>
<labelBounds x="-85" y="-31" width="84" height="30"/>
<noBackgroundColor>true</noBackgroundColor>
<noForegroundColor>true</noForegroundColor>
</centerLabel>
<points>
<point x="2436" y="2108"/>
<point x="2048" y="2406"/>
</points>
</Connector>
<Connector class="oracle.dbtools.crest.swingui.relational.TVFKRelation" oid="61D4C07C-A2BB-7417-E3A8-3F4AB0C3D7D4" otype="FKIndexAssociation" vid_source="681B5C5D-866E-D2EA-58E7-6B74CC242C90" vid_target="A25D8B15-42D0-A6E0-2533-B68A3E1B62DF">
<hideElementsInCurrentOnly>false</hideElementsInCurrentOnly>
<backgroundColor>-16777216</backgroundColor>
<lineWidth>1</lineWidth>
<centerLabel class="oracle.dbtools.crest.model.design.Label">
<site>1</site>
<labelBounds x="-101" y="-31" width="101" height="30"/>
<noBackgroundColor>true</noBackgroundColor>
<noForegroundColor>true</noForegroundColor>
</centerLabel>
<points>
<point x="3005" y="1729"/>
<point x="2259" y="1729"/>
</points>
</Connector>
<Connector class="oracle.dbtools.crest.swingui.relational.TVFKRelation" oid="6F83671F-EC15-853E-5878-760EB21F74E4" otype="FKIndexAssociation" vid_source="966ACDC1-7DCB-7798-79EB-A7880CC4D1C1" vid_target="C3DB015C-EA85-0F9A-678E-8C328DB104EC">
<hideElementsInCurrentOnly>false</hideElementsInCurrentOnly>
<backgroundColor>-16777216</backgroundColor>
<lineWidth>1</lineWidth>
<centerLabel class="oracle.dbtools.crest.model.design.Label">
<site>1</site>
<labelBounds x="-117" y="-31" width="117" height="30"/>
<noBackgroundColor>true</noBackgroundColor>
<noForegroundColor>true</noForegroundColor>
</centerLabel>
<points>
<point x="2424" y="791"/>
<point x="2230" y="791"/>
</points>
</Connector>
<Connector class="oracle.dbtools.crest.swingui.relational.TVFKRelation" oid="70362D0E-C09B-BFA2-AA00-464E2B56DEDC" otype="FKIndexAssociation" vid_source="B8E0C93C-5534-6B2D-DC1C-EBEC97E2AF24" vid_target="9DA066B0-E210-71E4-25EB-A97C92A81DF9">
<hideElementsInCurrentOnly>false</hideElementsInCurrentOnly>
<backgroundColor>-16777216</backgroundColor>
<lineWidth>1</lineWidth>
<centerLabel class="oracle.dbtools.crest.model.design.Label">
<site>1</site>
<labelBounds x="-95" y="-31" width="95" height="30"/>
<noBackgroundColor>true</noBackgroundColor>
<noForegroundColor>true</noForegroundColor>
</centerLabel>
<points>
<point x="1690" y="2372"/>
<point x="829" y="1353"/>
</points>
</Connector>
<Connector class="oracle.dbtools.crest.swingui.relational.TVFKRelation" oid="7A6E920D-F3CC-1494-3B48-DFED40F66575" otype="FKIndexAssociation" vid_source="B8E0C93C-5534-6B2D-DC1C-EBEC97E2AF24" vid_target="A25D8B15-42D0-A6E0-2533-B68A3E1B62DF">
<hideElementsInCurrentOnly>false</hideElementsInCurrentOnly>
<backgroundColor>-16777216</backgroundColor>
<lineWidth>1</lineWidth>
<centerLabel class="oracle.dbtools.crest.model.design.Label">
<site>1</site>
<labelBounds x="-67" y="-31" width="66" height="30"/>
<noBackgroundColor>true</noBackgroundColor>
<noForegroundColor>true</noForegroundColor>
</centerLabel>
<points>
<point x="1977" y="2372"/>
<point x="1977" y="2120"/>
</points>
</Connector>
<Connector class="oracle.dbtools.crest.swingui.relational.TVFKRelation" oid="7F9E629F-84AD-D69A-5DA4-B705767A8F8B" otype="FKIndexAssociation" vid_source="9DA066B0-E210-71E4-25EB-A97C92A81DF9" vid_target="F8342A33-0870-DFD8-27F8-639EE9B01088">
<hideElementsInCurrentOnly>false</hideElementsInCurrentOnly>
<backgroundColor>-16777216</backgroundColor>
<lineWidth>1</lineWidth>
<centerLabel class="oracle.dbtools.crest.model.design.Label">
<site>1</site>
<labelBounds x="-93" y="-31" width="92" height="30"/>
<noBackgroundColor>true</noBackgroundColor>
<noForegroundColor>true</noForegroundColor>
</centerLabel>
<points>
<point x="829" y="786"/>
<point x="1376" y="786"/>
</points>
</Connector>
<Connector class="oracle.dbtools.crest.swingui.relational.TVFKRelation" oid="80542217-C455-34E2-E255-1E40CDC4FBB1" otype="FKIndexAssociation" vid_source="B8E0C93C-5534-6B2D-DC1C-EBEC97E2AF24" vid_target="961EA11C-9323-C677-CA20-2F0045C0711A">
<hideElementsInCurrentOnly>false</hideElementsInCurrentOnly>
<backgroundColor>-16777216</backgroundColor>
<lineWidth>1</lineWidth>
<centerLabel class="oracle.dbtools.crest.model.design.Label">
<site>1</site>
<labelBounds x="-99" y="-31" width="98" height="30"/>
<noBackgroundColor>true</noBackgroundColor>
<noForegroundColor>true</noForegroundColor>
</centerLabel>
<points>
<point x="1656" y="2415"/>
<point x="1136" y="2040"/>
</points>
</Connector>
<Connector class="oracle.dbtools.crest.swingui.relational.TVFKRelation" oid="82B9BA39-A3A3-DF0C-7113-81EB861DF9F3" otype="FKIndexAssociation" vid_source="B8E0C93C-5534-6B2D-DC1C-EBEC97E2AF24" vid_target="E455054E-209D-8758-F0AA-C9367F92EBF3">
<hideElementsInCurrentOnly>false</hideElementsInCurrentOnly>
<backgroundColor>-16777216</backgroundColor>
<lineWidth>1</lineWidth>
<centerLabel class="oracle.dbtools.crest.model.design.Label">
<site>1</site>
<labelBounds x="-91" y="-31" width="91" height="30"/>
<noBackgroundColor>true</noBackgroundColor>
<noForegroundColor>true</noForegroundColor>
</centerLabel>
<points>
<point x="1754" y="2372"/>
<point x="1754" y="2123"/>
</points>
</Connector>
<Connector class="oracle.dbtools.crest.swingui.relational.TVFKRelation" oid="896FB382-9C2B-66A5-C712-822160E910E9" otype="FKIndexAssociation" vid_source="B8E0C93C-5534-6B2D-DC1C-EBEC97E2AF24" vid_target="BC9718B1-702B-391C-9972-6098DC19CD45">
<hideElementsInCurrentOnly>false</hideElementsInCurrentOnly>
<backgroundColor>-16777216</backgroundColor>
<lineWidth>1</lineWidth>
<centerLabel class="oracle.dbtools.crest.model.design.Label">
<site>1</site>
<labelBounds x="-91" y="-31" width="90" height="30"/>
<noBackgroundColor>true</noBackgroundColor>
<noForegroundColor>true</noForegroundColor>
</centerLabel>
<points>
<point x="1909" y="2742"/>
<point x="1909" y="2887"/>
</points>
</Connector>
<Connector class="oracle.dbtools.crest.swingui.relational.TVFKRelation" oid="8B618EFB-3501-11DB-9F30-714A3C40259C" otype="FKIndexAssociation" vid_source="966ACDC1-7DCB-7798-79EB-A7880CC4D1C1" vid_target="9DA066B0-E210-71E4-25EB-A97C92A81DF9">
<hideElementsInCurrentOnly>false</hideElementsInCurrentOnly>
<backgroundColor>-16777216</backgroundColor>
<lineWidth>1</lineWidth>
<centerLabel class="oracle.dbtools.crest.model.design.Label">
<site>1</site>
<labelBounds x="-147" y="-31" width="147" height="30"/>
<noBackgroundColor>true</noBackgroundColor>
<noForegroundColor>true</noForegroundColor>
</centerLabel>
<points>
<point x="2424" y="808"/>
<point x="829" y="808"/>
</points>
</Connector>
<Connector class="oracle.dbtools.crest.swingui.relational.TVFKRelation" oid="8C633A6A-9C6C-8E20-EBD4-6E1EE6136773" otype="FKIndexAssociation" vid_source="D7FB553C-F128-0BB8-EE80-FFCB02811AD1" vid_target="BC9718B1-702B-391C-9972-6098DC19CD45">
<hideElementsInCurrentOnly>false</hideElementsInCurrentOnly>
<backgroundColor>-16777216</backgroundColor>
<lineWidth>1</lineWidth>
<centerLabel class="oracle.dbtools.crest.model.design.Label">
<site>1</site>
<labelBounds x="-87" y="-31" width="86" height="30"/>
<noBackgroundColor>true</noBackgroundColor>
<noForegroundColor>true</noForegroundColor>
</centerLabel>
<points>
<point x="2512" y="3047"/>
<point x="2095" y="3047"/>
</points>
</Connector>
<Connector class="oracle.dbtools.crest.swingui.relational.TVFKRelation" oid="9938BF35-3628-8F15-CD48-A75E82AB90A6" otype="FKIndexAssociation" vid_source="9DA066B0-E210-71E4-25EB-A97C92A81DF9" vid_target="961EA11C-9323-C677-CA20-2F0045C0711A">
<hideElementsInCurrentOnly>false</hideElementsInCurrentOnly>
<backgroundColor>-16777216</backgroundColor>
<lineWidth>1</lineWidth>
<centerLabel class="oracle.dbtools.crest.model.design.Label">
<site>1</site>
<labelBounds x="-97" y="-31" width="96" height="30"/>
<noBackgroundColor>true</noBackgroundColor>
<noForegroundColor>true</noForegroundColor>
</centerLabel>
<points>
<point x="829" y="1713"/>
<point x="829" y="1774"/>
</points>
</Connector>
<Connector class="oracle.dbtools.crest.swingui.relational.TVFKRelation" oid="9F6BF0DA-8E84-8375-604E-B7CB4EEDFDBF" otype="FKIndexAssociation" vid_source="B8E0C93C-5534-6B2D-DC1C-EBEC97E2AF24" vid_target="980E517A-93CC-EABF-09BC-A46036512BA8">
<hideElementsInCurrentOnly>false</hideElementsInCurrentOnly>
<backgroundColor>-16777216</backgroundColor>
<lineWidth>1</lineWidth>
<centerLabel class="oracle.dbtools.crest.model.design.Label">
<site>1</site>
<labelBounds x="-65" y="-31" width="65" height="30"/>
<noBackgroundColor>true</noBackgroundColor>
<noForegroundColor>true</noForegroundColor>
</centerLabel>
<points>
<point x="1656" y="2376"/>
<point x="1337" y="2376"/>
</points>
</Connector>
<Connector class="oracle.dbtools.crest.swingui.relational.TVFKRelation" oid="A3373EA7-15C5-6165-A45E-5F01A6683706" otype="FKIndexAssociation" vid_source="B8E0C93C-5534-6B2D-DC1C-EBEC97E2AF24" vid_target="F8342A33-0870-DFD8-27F8-639EE9B01088">
<hideElementsInCurrentOnly>false</hideElementsInCurrentOnly>
<backgroundColor>-16777216</backgroundColor>
<lineWidth>1</lineWidth>
<centerLabel class="oracle.dbtools.crest.model.design.Label">
<site>1</site>
<labelBounds x="-109" y="-31" width="109" height="30"/>
<noBackgroundColor>true</noBackgroundColor>
<noForegroundColor>true</noForegroundColor>
</centerLabel>
<points>
<point x="1703" y="2372"/>
<point x="1703" y="923"/>
</points>
</Connector>
<Connector class="oracle.dbtools.crest.swingui.relational.TVFKRelation" oid="AA3AE612-4D9E-B6AA-DC3B-DCBB634E9E2B" otype="FKIndexAssociation" vid_source="B8E0C93C-5534-6B2D-DC1C-EBEC97E2AF24" vid_target="9DA066B0-E210-71E4-25EB-A97C92A81DF9">
<hideElementsInCurrentOnly>false</hideElementsInCurrentOnly>
<backgroundColor>-16777216</backgroundColor>
<lineWidth>1</lineWidth>
<centerLabel class="oracle.dbtools.crest.model.design.Label">
<site>1</site>
<labelBounds x="-89" y="-31" width="88" height="30"/>
<noBackgroundColor>true</noBackgroundColor>
<noForegroundColor>true</noForegroundColor>
</centerLabel>
<points>
<point x="1690" y="2372"/>
<point x="829" y="1338"/>
</points>
</Connector>
<Connector class="oracle.dbtools.crest.swingui.relational.TVFKRelation" oid="AC1CD0C0-7FB5-81B9-359F-A6B43CF097FF" otype="FKIndexAssociation" vid_source="9DA066B0-E210-71E4-25EB-A97C92A81DF9" vid_target="C3DB015C-EA85-0F9A-678E-8C328DB104EC">
<hideElementsInCurrentOnly>false</hideElementsInCurrentOnly>
<backgroundColor>-16777216</backgroundColor>
<lineWidth>1</lineWidth>
<centerLabel class="oracle.dbtools.crest.model.design.Label">
<site>1</site>
<labelBounds x="-103" y="-31" width="103" height="30"/>
<noBackgroundColor>true</noBackgroundColor>
<noForegroundColor>true</noForegroundColor>
</centerLabel>
<points>
<point x="829" y="831"/>
<point x="1860" y="831"/>
</points>
</Connector>
<Connector class="oracle.dbtools.crest.swingui.relational.TVFKRelation" oid="B3408B93-C6B0-34D4-9138-4E8F0CB32526" otype="FKIndexAssociation" vid_source="B8E0C93C-5534-6B2D-DC1C-EBEC97E2AF24" vid_target="961EA11C-9323-C677-CA20-2F0045C0711A">
<hideElementsInCurrentOnly>false</hideElementsInCurrentOnly>
<backgroundColor>-16777216</backgroundColor>
<lineWidth>1</lineWidth>
<centerLabel class="oracle.dbtools.crest.model.design.Label">
<site>1</site>
<labelBounds x="-109" y="-31" width="108" height="30"/>
<noBackgroundColor>true</noBackgroundColor>
<noForegroundColor>true</noForegroundColor>
</centerLabel>
<points>
<point x="1656" y="2415"/>
<point x="1136" y="2040"/>
</points>
</Connector>
<Connector class="oracle.dbtools.crest.swingui.relational.TVFKRelation" oid="B64126D1-D394-0D4B-A851-E9C9C002F45B" otype="FKIndexAssociation" vid_source="B8E0C93C-5534-6B2D-DC1C-EBEC97E2AF24" vid_target="C3DB015C-EA85-0F9A-678E-8C328DB104EC">
<hideElementsInCurrentOnly>false</hideElementsInCurrentOnly>
<backgroundColor>-16777216</backgroundColor>
<lineWidth>1</lineWidth>
<centerLabel class="oracle.dbtools.crest.model.design.Label">
<site>1</site>
<labelBounds x="-113" y="-31" width="112" height="30"/>
<noBackgroundColor>true</noBackgroundColor>
<noForegroundColor>true</noForegroundColor>
</centerLabel>
<points>
<point x="1939" y="2372"/>
<point x="1939" y="1012"/>
</points>
</Connector>
<Connector class="oracle.dbtools.crest.swingui.relational.TVFKRelation" oid="BB5181A6-67C7-C853-06B8-F5EE899CF9E8" otype="FKIndexAssociation" vid_source="9DA066B0-E210-71E4-25EB-A97C92A81DF9" vid_target="208205D6-BB37-5991-61BB-5FFC6A0020E8">
<hideElementsInCurrentOnly>false</hideElementsInCurrentOnly>
<backgroundColor>-16777216</backgroundColor>
<lineWidth>1</lineWidth>
<centerLabel class="oracle.dbtools.crest.model.design.Label">
<site>1</site>
<labelBounds x="-75" y="-31" width="74" height="30"/>
<noBackgroundColor>true</noBackgroundColor>
<noForegroundColor>true</noForegroundColor>
</centerLabel>
<points>
<point x="476" y="1081"/>
<point x="326" y="1081"/>
</points>
</Connector>
<Connector class="oracle.dbtools.crest.swingui.relational.TVFKRelation" oid="BD061BC5-0409-01F6-94B7-1141F49FECE0" otype="FKIndexAssociation" vid_source="EBCB4760-6EE8-4118-49D2-FE8E6B67D156" vid_target="1D555976-D44B-2C4F-C70D-DFE5CB8B4AD2">
<hideElementsInCurrentOnly>false</hideElementsInCurrentOnly>
<backgroundColor>-16777216</backgroundColor>
<lineWidth>1</lineWidth>
<centerLabel class="oracle.dbtools.crest.model.design.Label">
<site>1</site>
<labelBounds x="-77" y="-31" width="77" height="30"/>
<noBackgroundColor>true</noBackgroundColor>
<noForegroundColor>true</noForegroundColor>
</centerLabel>
<points>
<point x="2816" y="1920"/>
<point x="3001" y="1920"/>
</points>
</Connector>
<Connector class="oracle.dbtools.crest.swingui.relational.TVFKRelation" oid="BD7EE11A-C88B-3F22-6FE1-61E82C9C9DB0" otype="FKIndexAssociation" vid_source="B8E0C93C-5534-6B2D-DC1C-EBEC97E2AF24" vid_target="4336DF47-1917-A176-1867-DC74E2ABC491">
<hideElementsInCurrentOnly>false</hideElementsInCurrentOnly>
<backgroundColor>-16777216</backgroundColor>
<lineWidth>1</lineWidth>
<centerLabel class="oracle.dbtools.crest.model.design.Label">
<site>1</site>
<labelBounds x="-65" y="-31" width="65" height="30"/>
<noBackgroundColor>true</noBackgroundColor>
<noForegroundColor>true</noForegroundColor>
</centerLabel>
<points>
<point x="1656" y="2557"/>
<point x="1317" y="2557"/>
</points>
</Connector>
<Connector class="oracle.dbtools.crest.swingui.relational.TVFKRelation" oid="C41836B1-BB46-5E60-D0D0-FD6440992209" otype="FKIndexAssociation" vid_source="9DA066B0-E210-71E4-25EB-A97C92A81DF9" vid_target="E455054E-209D-8758-F0AA-C9367F92EBF3">
<hideElementsInCurrentOnly>false</hideElementsInCurrentOnly>
<backgroundColor>-16777216</backgroundColor>
<lineWidth>1</lineWidth>
<centerLabel class="oracle.dbtools.crest.model.design.Label">
<site>1</site>
<labelBounds x="-89" y="-31" width="89" height="30"/>
<noBackgroundColor>true</noBackgroundColor>
<noForegroundColor>true</noForegroundColor>
</centerLabel>
<points>
<point x="829" y="1312"/>
<point x="1501" y="1809"/>
</points>
</Connector>
<Connector class="oracle.dbtools.crest.swingui.relational.TVFKRelation" oid="D6C2D5DE-564D-C2E2-083C-C2761D27A2DA" otype="FKIndexAssociation" vid_source="EBCB4760-6EE8-4118-49D2-FE8E6B67D156" vid_target="681B5C5D-866E-D2EA-58E7-6B74CC242C90">
<hideElementsInCurrentOnly>false</hideElementsInCurrentOnly>
<backgroundColor>-16777216</backgroundColor>
<lineWidth>1</lineWidth>
<centerLabel class="oracle.dbtools.crest.model.design.Label">
<site>1</site>
<labelBounds x="-73" y="-31" width="73" height="30"/>
<noBackgroundColor>true</noBackgroundColor>
<noForegroundColor>true</noForegroundColor>
</centerLabel>
<points>
<point x="2816" y="1716"/>
<point x="3005" y="1716"/>
</points>
</Connector>
<Connector class="oracle.dbtools.crest.swingui.relational.TVFKRelation" oid="E921691F-FAA2-FE7B-7DCE-33EF0ACF96F3" otype="FKIndexAssociation" vid_source="EBCB4760-6EE8-4118-49D2-FE8E6B67D156" vid_target="BA7581E3-C45F-CE3E-8CE5-477A6EEAB6B4">
<hideElementsInCurrentOnly>false</hideElementsInCurrentOnly>
<backgroundColor>-16777216</backgroundColor>
<lineWidth>1</lineWidth>
<centerLabel class="oracle.dbtools.crest.model.design.Label">
<site>1</site>
<labelBounds x="-97" y="-31" width="97" height="30"/>
<noBackgroundColor>true</noBackgroundColor>
<noForegroundColor>true</noForegroundColor>
</centerLabel>
<points>
<point x="2816" y="2167"/>
<point x="2980" y="2167"/>
</points>
</Connector>
<Connector class="oracle.dbtools.crest.swingui.relational.TVFKRelation" oid="F3C5A71B-C5B3-98B4-FAE0-7B50D7B63B75" otype="FKIndexAssociation" vid_source="EBCB4760-6EE8-4118-49D2-FE8E6B67D156" vid_target="9DA066B0-E210-71E4-25EB-A97C92A81DF9">
<hideElementsInCurrentOnly>false</hideElementsInCurrentOnly>
<backgroundColor>-16777216</backgroundColor>
<lineWidth>1</lineWidth>
<centerLabel class="oracle.dbtools.crest.model.design.Label">
<site>1</site>
<labelBounds x="-89" y="-31" width="89" height="30"/>
<noBackgroundColor>true</noBackgroundColor>
<noForegroundColor>true</noForegroundColor>
</centerLabel>
<points>
<point x="2436" y="1704"/>
<point x="829" y="1704"/>
</points>
</Connector>
</connectors>
</Diagram>
